alu_netlist.v
/* Generated by Yosys 0.66+179 (git sha1 e74db6dea, Release, GNU /usr/bin/x86_64-w64-mingw32-g++ 13.2.1) */

(* top =  1  *)
(* src = "alu.v:1.1-21.10" *)
module alu(A, B, Sel, Result);
  (* src = "alu.v:2.17-2.18" *)
  input [7:0] A;
  wire [7:0] A;
  (* src = "alu.v:3.17-3.18" *)
  input [7:0] B;
  wire [7:0] B;
  (* src = "alu.v:4.17-4.20" *)
  input [2:0] Sel;
  wire [2:0] Sel;
  (* src = "alu.v:5.22-5.28" *)
  output [7:0] Result;
  wire [7:0] Result;
  wire _000_;
  wire _001_;
  wire _002_;
  wire _003_;
  wire _004_;
  wire _005_;
  wire _006_;
  wire _007_;
  wire _008_;
  wire _009_;
  wire _010_;
  wire _011_;
  wire _012_;
  wire _013_;
  wire _014_;
  wire _015_;
  wire _016_;
  wire _017_;
  wire _018_;
  wire _019_;
  wire _020_;
  wire _021_;
  wire _022_;
  wire _023_;
  wire _024_;
  wire _025_;
  wire _026_;
  wire _027_;
  wire _028_;
  wire _029_;
  wire _030_;
  wire _031_;
  wire _032_;
  wire _033_;
  wire _034_;
  wire _035_;
  wire _036_;
  wire _037_;
  wire _038_;
  wire _039_;
  wire _040_;
  wire _041_;
  wire _042_;
  wire _043_;
  wire _044_;
  wire _045_;
  wire _046_;
  wire _047_;
  wire _048_;
  wire _049_;
  wire _050_;
  wire _051_;
  wire _052_;
  wire _053_;
  wire _054_;
  wire _055_;
  wire _056_;
  wire _057_;
  wire _058_;
  wire _059_;
  wire _060_;
  wire _061_;
  wire _062_;
  wire _063_;
  wire _064_;
  wire _065_;
  wire _066_;
  wire _067_;
  wire _068_;
  wire _069_;
  wire _070_;
  wire _071_;
  wire _072_;
  wire _073_;
  wire _074_;
  wire _075_;
  wire _076_;
  wire _077_;
  wire _078_;
  wire _079_;
  wire _080_;
  wire _081_;
  wire _082_;
  wire _083_;
  wire _084_;
  wire _085_;
  wire _086_;
  wire _087_;
  wire _088_;
  wire _089_;
  wire _090_;
  wire _091_;
  wire _092_;
  wire _093_;
  wire _094_;
  wire _095_;
  wire _096_;
  wire _097_;
  wire _098_;
  wire _099_;
  wire _100_;
  wire _101_;
  wire _102_;
  wire _103_;
  wire _104_;
  wire _105_;
  wire _106_;
  wire _107_;
  wire _108_;
  wire _109_;
  wire _110_;
  wire _111_;
  wire _112_;
  wire _113_;
  wire _114_;
  wire _115_;
  wire _116_;
  wire _117_;
  wire _118_;
  wire _119_;
  wire _120_;
  wire _121_;
  wire _122_;
  wire _123_;
  wire _124_;
  wire _125_;
  wire _126_;
  wire _127_;
  wire _128_;
  wire _129_;
  wire _130_;
  wire _131_;
  wire _132_;
  wire _133_;
  wire _134_;
  wire _135_;
  wire _136_;
  wire _137_;
  wire _138_;
  wire _139_;
  wire _140_;
  wire _141_;
  wire _142_;
  wire _143_;
  wire _144_;
  wire _145_;
  wire _146_;
  wire _147_;
  wire _148_;
  wire _149_;
  wire _150_;
  wire _151_;
  wire _152_;
  wire _153_;
  wire _154_;
  wire _155_;
  wire _156_;
  wire _157_;
  wire _158_;
  wire _159_;
  wire _160_;
  wire _161_;
  wire _162_;
  wire _163_;
  wire _164_;
  wire _165_;
  wire _166_;
  wire _167_;
  wire _168_;
  wire _169_;
  wire _170_;
  wire _171_;
  assign _100_ = ~Sel[2];
  assign _101_ = Sel[1] | ~(Sel[0]);
  assign _102_ = Sel[2] | _101_;
  assign _103_ = B[1] | B[0];
  assign _104_ = B[2] | _103_;
  assign _105_ = B[3] | _104_;
  assign _106_ = B[4] | _105_;
  assign _107_ = B[0] & _102_;
  assign _108_ = _102_ & _103_;
  assign _109_ = _102_ & _104_;
  assign _110_ = _102_ & _105_;
  assign _111_ = _102_ & _106_;
  assign _112_ = B[5] | _111_;
  assign _113_ = ~(B[5] ^ _111_);
  assign _114_ = ~(A[5] & _113_);
  assign _115_ = A[5] ^ _113_;
  assign _116_ = ~(B[4] ^ _110_);
  assign _117_ = ~(A[4] & _116_);
  assign _118_ = ~(B[3] ^ _109_);
  assign _119_ = ~(A[3] & _118_);
  assign _120_ = ~(A[3] ^ _118_);
  assign _121_ = ~(B[2] ^ _108_);
  assign _122_ = ~(A[2] & _121_);
  assign _123_ = ~(B[1] ^ _107_);
  assign _124_ = ~(A[1] & _123_);
  assign _125_ = A[0] | B[0];
  assign _126_ = A[0] & B[0];
  assign _127_ = _125_ & ~(_126_);
  assign _128_ = B[0] & ~(A[0]);
  assign _129_ = ~(A[1] ^ _123_);
  assign _130_ = _128_ | _129_;
  assign _131_ = ~(_124_ & _130_);
  assign _132_ = A[2] ^ _121_;
  assign _133_ = ~(_131_ & _132_);
  assign _134_ = _122_ & _133_;
  assign _135_ = _120_ | _134_;
  assign _136_ = ~(_119_ & _135_);
  assign _137_ = A[4] ^ _116_;
  assign _138_ = ~(_136_ & _137_);
  assign _139_ = ~(_117_ & _138_);
  assign _140_ = ~(_115_ & _139_);
  assign _141_ = ~(_114_ & _140_);
  assign _142_ = _102_ & _112_;
  assign _143_ = ~(B[6] ^ _142_);
  assign _144_ = ~(A[6] & _143_);
  assign _145_ = A[6] ^ _143_;
  assign _146_ = ~(_141_ & _145_);
  assign _147_ = Sel[1] | Sel[0];
  assign _148_ = ~(_102_ & _147_);
  assign _149_ = ~(Sel[1] | Sel[2]);
  assign _150_ = _141_ ^ _145_;
  assign _151_ = ~(_149_ & _150_);
  assign _152_ = A[6] | B[6];
  assign _153_ = Sel[1] & Sel[0];
  assign _154_ = _100_ & _153_;
  assign _155_ = ~(A[6] & B[6]);
  assign _156_ = Sel[2] & ~(_147_);
  assign _157_ = _155_ & _156_;
  assign _158_ = _154_ | _157_;
  assign _159_ = ~(_152_ & _158_);
  assign _160_ = Sel[1] & ~(Sel[0]);
  assign _161_ = _100_ & _160_;
  assign _162_ = _155_ | ~(_161_);
  assign _163_ = _100_ | _101_;
  assign _164_ = A[6] | _163_;
  assign _165_ = _162_ & _164_;
  assign _166_ = Sel[2] & _160_;
  assign _167_ = ~(A[5] & _166_);
  assign _168_ = Sel[2] & _153_;
  assign _169_ = ~(A[7] & _168_);
  assign _170_ = _167_ & _169_;
  assign _171_ = _165_ & _170_;
  assign _000_ = _159_ & _171_;
  assign Result[6] = ~(_151_ & _000_);
  assign _001_ = _115_ ^ _139_;
  assign _002_ = ~(_149_ & _001_);
  assign _003_ = A[5] | B[5];
  assign _004_ = ~(A[5] & B[5]);
  assign _005_ = ~(A[4] & _166_);
  assign _006_ = ~(A[6] & _168_);
  assign _007_ = A[5] | _163_;
  assign _008_ = _156_ & _003_;
  assign _009_ = _004_ ? _008_ : _161_;
  assign _010_ = _005_ & _006_;
  assign _011_ = ~(_154_ & _003_);
  assign _012_ = ~(_007_ & _011_);
  assign _013_ = ~(_009_ | _012_);
  assign _014_ = _010_ & _013_;
  assign Result[5] = ~(_002_ & _014_);
  assign _015_ = _136_ ^ _137_;
  assign _016_ = ~(_149_ & _015_);
  assign _017_ = A[4] | B[4];
  assign _018_ = ~(A[4] & B[4]);
  assign _019_ = ~(A[3] & _166_);
  assign _020_ = ~(A[5] & _168_);
  assign _021_ = A[4] | _163_;
  assign _022_ = _156_ & _017_;
  assign _023_ = _018_ ? _022_ : _161_;
  assign _024_ = _019_ & _020_;
  assign _025_ = ~(_154_ & _017_);
  assign _026_ = ~(_021_ & _025_);
  assign _027_ = ~(_023_ | _026_);
  assign _028_ = _024_ & _027_;
  assign Result[4] = ~(_016_ & _028_);
  assign _029_ = _120_ ^ _134_;
  assign _030_ = ~(_149_ & _029_);
  assign _031_ = B[3] | A[3];
  assign _032_ = B[3] & A[3];
  assign _033_ = _156_ & ~(_032_);
  assign _034_ = _154_ | _033_;
  assign _035_ = ~(_031_ & _034_);
  assign _036_ = ~(A[4] & _168_);
  assign _037_ = ~(_161_ & _032_);
  assign _038_ = ~(A[2] & _166_);
  assign _039_ = A[3] | _163_;
  assign _040_ = _036_ & _039_;
  assign _041_ = _037_ & _038_;
  assign _042_ = _040_ & _041_;
  assign _043_ = _035_ & _042_;
  assign Result[3] = ~(_030_ & _043_);
  assign _044_ = _131_ ^ _132_;
  assign _045_ = ~(_149_ & _044_);
  assign _046_ = A[2] & B[2];
  assign _047_ = ~(_161_ & _046_);
  assign _048_ = A[2] | _163_;
  assign _049_ = A[2] | B[2];
  assign _050_ = ~(_154_ & _049_);
  assign _051_ = ~(A[1] & _166_);
  assign _052_ = _050_ & _051_;
  assign _053_ = A[2] ^ B[2];
  assign _054_ = ~(_156_ & _053_);
  assign _055_ = ~(A[3] & _168_);
  assign _056_ = _047_ & _054_;
  assign _057_ = _048_ & _055_;
  assign _058_ = _056_ & _057_;
  assign _059_ = _052_ & _058_;
  assign Result[2] = ~(_045_ & _059_);
  assign _060_ = _128_ ^ _129_;
  assign _061_ = ~(_149_ & _060_);
  assign _062_ = A[1] | B[1];
  assign _063_ = ~(_154_ & _062_);
  assign _064_ = ~(A[1] & B[1]);
  assign _065_ = ~(A[0] & _166_);
  assign _066_ = A[1] | _163_;
  assign _067_ = _065_ & _066_;
  assign _068_ = ~(A[2] & _168_);
  assign _069_ = _156_ & _062_;
  assign _070_ = _064_ ? _069_ : _161_;
  assign _071_ = _063_ & _068_;
  assign _072_ = _067_ & ~(_070_);
  assign _073_ = _071_ & _072_;
  assign Result[1] = ~(_061_ & _073_);
  assign _074_ = ~(_127_ & _148_);
  assign _075_ = ~(_125_ & _154_);
  assign _076_ = ~(_126_ & _161_);
  assign _077_ = _075_ & _076_;
  assign _078_ = ~(A[1] & _168_);
  assign _079_ = A[0] | _163_;
  assign _080_ = _078_ & _079_;
  assign _081_ = _077_ & _080_;
  assign Result[0] = ~(_074_ & _081_);
  assign _082_ = ~(_144_ & _146_);
  assign _083_ = A[7] | B[7];
  assign _084_ = A[7] & B[7];
  assign _085_ = _083_ & ~(_084_);
  assign _086_ = B[6] | _112_;
  assign _087_ = ~(_102_ & _086_);
  assign _088_ = ~(_085_ ^ _087_);
  assign _089_ = ~(_082_ ^ _088_);
  assign _090_ = ~(_149_ & _089_);
  assign _091_ = ~(_154_ & _083_);
  assign _092_ = ~(_156_ & _085_);
  assign _093_ = _091_ & _092_;
  assign _094_ = ~(A[6] & _166_);
  assign _095_ = A[7] | _163_;
  assign _096_ = ~(_161_ & _084_);
  assign _097_ = _095_ & _096_;
  assign _098_ = _093_ & _097_;
  assign _099_ = _094_ & _098_;
  assign Result[7] = ~(_090_ & _099_);
endmodule

alu_tb.v
`timescale 1ns/1ps

module alu_tb;

reg [7:0] A, B;
reg [2:0] Sel;
wire [7:0] Result;

alu uut (
    .A(A),
    .B(B),
    .Sel(Sel),
    .Result(Result)
);

integer i;

initial begin

    $dumpfile("alu.vcd");
    $dumpvars(0, alu_tb);

    A = 8'd10;
    B = 8'd5;

    for(i=0; i<8; i=i+1) begin
        Sel = i;
        #10;
    end

    // Random Tests
    repeat(10) begin
        A = $random;
        B = $random;
        Sel = $random % 8;
        #10;
    end

    $finish;

end

endmodule

alu.vcd
$date
	Sun Jun 28 16:30:08 2026
$end
$version
	Icarus Verilog
$end
$timescale
	1ps
$end
$scope module alu_tb $end
$var wire 8 ! Result [7:0] $end
$var reg 8 " A [7:0] $end
$var reg 8 # B [7:0] $end
$var reg 3 $ Sel [2:0] $end
$var integer 32 % i [31:0] $end
$scope module uut $end
$var wire 8 & A [7:0] $end
$var wire 8 ' B [7:0] $end
$var wire 3 ( Sel [2:0] $end
$var wire 1 ) _000_ $end
$var wire 1 * _001_ $end
$var wire 1 + _002_ $end
$var wire 1 , _003_ $end
$var wire 1 - _004_ $end
$var wire 1 . _005_ $end
$var wire 1 / _006_ $end
$var wire 1 0 _007_ $end
$var wire 1 1 _008_ $end
$var wire 1 2 _010_ $end
$var wire 1 3 _011_ $end
$var wire 1 4 _012_ $end
$var wire 1 5 _013_ $end
$var wire 1 6 _014_ $end
$var wire 1 7 _015_ $end
$var wire 1 8 _016_ $end
$var wire 1 9 _017_ $end
$var wire 1 : _018_ $end
$var wire 1 ; _019_ $end
$var wire 1 < _020_ $end
$var wire 1 = _021_ $end
$var wire 1 > _022_ $end
$var wire 1 ? _024_ $end
$var wire 1 @ _025_ $end
$var wire 1 A _026_ $end
$var wire 1 B _027_ $end
$var wire 1 C _028_ $end
$var wire 1 D _029_ $end
$var wire 1 E _030_ $end
$var wire 1 F _031_ $end
$var wire 1 G _032_ $end
$var wire 1 H _033_ $end
$var wire 1 I _034_ $end
$var wire 1 J _035_ $end
$var wire 1 K _036_ $end
$var wire 1 L _037_ $end
$var wire 1 M _038_ $end
$var wire 1 N _039_ $end
$var wire 1 O _040_ $end
$var wire 1 P _041_ $end
$var wire 1 Q _042_ $end
$var wire 1 R _043_ $end
$var wire 1 S _044_ $end
$var wire 1 T _045_ $end
$var wire 1 U _046_ $end
$var wire 1 V _047_ $end
$var wire 1 W _048_ $end
$var wire 1 X _049_ $end
$var wire 1 Y _050_ $end
$var wire 1 Z _051_ $end
$var wire 1 [ _052_ $end
$var wire 1 \ _053_ $end
$var wire 1 ] _054_ $end
$var wire 1 ^ _055_ $end
$var wire 1 _ _056_ $end
$var wire 1 ` _057_ $end
$var wire 1 a _058_ $end
$var wire 1 b _059_ $end
$var wire 1 c _060_ $end
$var wire 1 d _061_ $end
$var wire 1 e _062_ $end
$var wire 1 f _063_ $end
$var wire 1 g _064_ $end
$var wire 1 h _065_ $end
$var wire 1 i _066_ $end
$var wire 1 j _067_ $end
$var wire 1 k _068_ $end
$var wire 1 l _069_ $end
$var wire 1 m _071_ $end
$var wire 1 n _072_ $end
$var wire 1 o _073_ $end
$var wire 1 p _074_ $end
$var wire 1 q _075_ $end
$var wire 1 r _076_ $end
$var wire 1 s _077_ $end
$var wire 1 t _078_ $end
$var wire 1 u _079_ $end
$var wire 1 v _080_ $end
$var wire 1 w _081_ $end
$var wire 1 x _082_ $end
$var wire 1 y _083_ $end
$var wire 1 z _084_ $end
$var wire 1 { _085_ $end
$var wire 1 | _086_ $end
$var wire 1 } _087_ $end
$var wire 1 ~ _088_ $end
$var wire 1 !" _089_ $end
$var wire 1 "" _090_ $end
$var wire 1 #" _091_ $end
$var wire 1 $" _092_ $end
$var wire 1 %" _093_ $end
$var wire 1 &" _094_ $end
$var wire 1 '" _095_ $end
$var wire 1 (" _096_ $end
$var wire 1 )" _097_ $end
$var wire 1 *" _098_ $end
$var wire 1 +" _099_ $end
$var wire 1 ," _100_ $end
$var wire 1 -" _101_ $end
$var wire 1 ." _102_ $end
$var wire 1 /" _103_ $end
$var wire 1 0" _104_ $end
$var wire 1 1" _105_ $end
$var wire 1 2" _106_ $end
$var wire 1 3" _107_ $end
$var wire 1 4" _108_ $end
$var wire 1 5" _109_ $end
$var wire 1 6" _110_ $end
$var wire 1 7" _111_ $end
$var wire 1 8" _112_ $end
$var wire 1 9" _113_ $end
$var wire 1 :" _114_ $end
$var wire 1 ;" _115_ $end
$var wire 1 <" _116_ $end
$var wire 1 =" _117_ $end
$var wire 1 >" _118_ $end
$var wire 1 ?" _119_ $end
$var wire 1 @" _120_ $end
$var wire 1 A" _121_ $end
$var wire 1 B" _122_ $end
$var wire 1 C" _123_ $end
$var wire 1 D" _124_ $end
$var wire 1 E" _125_ $end
$var wire 1 F" _126_ $end
$var wire 1 G" _127_ $end
$var wire 1 H" _128_ $end
$var wire 1 I" _129_ $end
$var wire 1 J" _130_ $end
$var wire 1 K" _131_ $end
$var wire 1 L" _132_ $end
$var wire 1 M" _133_ $end
$var wire 1 N" _134_ $end
$var wire 1 O" _135_ $end
$var wire 1 P" _136_ $end
$var wire 1 Q" _137_ $end
$var wire 1 R" _138_ $end
$var wire 1 S" _139_ $end
$var wire 1 T" _140_ $end
$var wire 1 U" _141_ $end
$var wire 1 V" _142_ $end
$var wire 1 W" _143_ $end
$var wire 1 X" _144_ $end
$var wire 1 Y" _145_ $end
$var wire 1 Z" _146_ $end
$var wire 1 [" _147_ $end
$var wire 1 \" _148_ $end
$var wire 1 ]" _149_ $end
$var wire 1 ^" _150_ $end
$var wire 1 _" _151_ $end
$var wire 1 `" _152_ $end
$var wire 1 a" _153_ $end
$var wire 1 b" _154_ $end
$var wire 1 c" _155_ $end
$var wire 1 d" _156_ $end
$var wire 1 e" _157_ $end
$var wire 1 f" _158_ $end
$var wire 1 g" _159_ $end
$var wire 1 h" _160_ $end
$var wire 1 i" _161_ $end
$var wire 1 j" _162_ $end
$var wire 1 k" _163_ $end
$var wire 1 l" _164_ $end
$var wire 1 m" _165_ $end
$var wire 1 n" _166_ $end
$var wire 1 o" _167_ $end
$var wire 1 p" _168_ $end
$var wire 1 q" _169_ $end
$var wire 1 r" _170_ $end
$var wire 1 s" _171_ $end
$var wire 1 t" _070_ $end
$var wire 1 u" _023_ $end
$var wire 1 v" _009_ $end
$var wire 8 w" Result [7:0] $end
$upscope $end
$upscope $end
$enddefinitions $end
$comment Show the parameter values. $end
$dumpall
$end
#0
$dumpvars
b1111 w"
0v"
0u"
0t"
1s"
1r"
1q"
0p"
1o"
0n"
1m"
1l"
1k"
1j"
0i"
0h"
1g"
0f"
0e"
0d"
1c"
0b"
0a"
0`"
1_"
0^"
1]"
1\"
0["
1Z"
0Y"
1X"
0W"
1V"
0U"
1T"
0S"
1R"
0Q"
0P"
1O"
1N"
1M"
1L"
0K"
1J"
0I"
1H"
1G"
0F"
1E"
1D"
0C"
1B"
1A"
0@"
1?"
0>"
1="
0<"
0;"
1:"
09"
18"
17"
16"
15"
14"
13"
12"
11"
10"
1/"
1."
1-"
1,"
1+"
1*"
1)"
1("
1'"
1&"
1%"
1$"
1#"
1""
0!"
1~
0}
1|
0{
0z
0y
0x
1w
1v
1u
1t
1s
1r
1q
0p
1o
1n
1m
0l
1k
1j
1i
1h
1g
1f
1e
0d
1c
1b
1a
1`
1_
1^
1]
1\
1[
1Z
1Y
1X
1W
1V
0U
0T
1S
1R
1Q
1P
1O
1N
1M
1L
1K
1J
0I
0H
0G
1F
0E
1D
1C
1B
0A
1@
1?
0>
1=
1<
1;
1:
09
18
07
16
15
04
13
12
01
10
1/
1.
1-
0,
1+
0*
1)
b0 (
b101 '
b1010 &
b0 %
b0 $
b101 #
b1010 "
b1111 !
$end
#10000
1x
0Z"
1U"
0T"
1S"
0R"
1d
1E
1""
1K"
0T
1P"
18
1+
1_"
0c
0D
0!"
b101 !
b101 w"
0D"
1I"
1S
0?"
1@"
07
0*
0^"
0L"
1Q"
1;"
1Y"
0~
1C"
0A"
1>"
1<"
0|
19"
1W"
08"
1}
0p
03"
04"
05"
06"
07"
0V"
0."
1\"
0-"
1["
b1 $
b1 (
b1 %
#20000
0x
0!"
1O"
0S"
1Z"
0U"
0K"
1N"
0P"
0^"
1~
1c
1M"
1D
1R"
0Y"
1T"
b0 !
b0 w"
1D"
0I"
1S
1?"
0@"
07
0W"
0}
0*
1L"
0Q"
0;"
1p
0C"
1A"
0>"
0<"
1V"
1|
09"
18"
0\"
1T
13"
14"
15"
16"
17"
1."
0]"
1i"
1-"
1h"
b10 $
b10 (
b10 %
#30000
b1111 !
b1111 w"
0R
0b
0o
0w
0J
0[
0m
0s
0Y
0f
0q
1f"
1I
0i"
1b"
0h"
1a"
b11 $
b11 (
b11 %
#40000
b1111 !
b1111 w"
0n
0b
0_
0R
0o
1w
0p
0]
1t"
0J
1[
1m
1s
0a
1e"
1H
1l
1Y
1f
1q
1`
1v
1\"
1d"
1f"
1I
1^
1t
0b"
0,"
0["
0a"
0p"
b100 $
b100 (
b100 %
#50000
06
0C
b11110101 !
b11110101 w"
05
0B
1R
1o
0)
0+"
1J
1n
0s"
14
1A
0w
0*"
1_
0m"
0`
0v
0)"
1p
0f"
0I
1]
0t"
0l"
00
0=
0W
0u
0'"
0e"
0H
0l
0k"
0\"
0d"
0-"
1["
b101 $
b101 (
b101 %
#60000
b10100 !
b10100 w"
16
15
1B
1)
1+"
1s"
04
0A
1a
1w
1*"
0?
0[
1m"
1`
1v
1)"
0;
0Z
1l"
10
1=
1W
1u
1'"
1k"
1n"
1-"
1h"
b110 $
b110 (
b110 %
#70000
b101 !
b101 w"
1C
0a
0w
1?
1[
0`
0v
1;
1Z
0^
0t
0n"
1p"
0h"
1a"
b111 $
b111 (
b111 %
#80000
1S"
0R"
1x
1P"
0Z"
0d
0O"
18
1U"
1_"
0""
b10100011 !
b10100011 w"
07
0:"
0^"
1Q"
1Y"
0p
0D
1T
1!"
1C"
1>"
1<"
0|
19"
1W"
1b
08"
1\"
1}
1E
1~
0+
1C
1a
1o
1w
03"
04"
05"
06"
07"
0V"
0N"
1c
1?
1`
1m
1v
0."
1]"
1A"
1{
1*
0@"
0B"
0I"
0S
1<
1^
1k
1t
1,"
0-"
0a"
0p"
1y
0;"
0L"
1,
0F
0e
b1 $
b1 (
b10000001 #
b10000001 '
b100100 "
b100100 &
b1000 %
#90000
0x
0U"
17
0S"
0C
b10011100 !
b10011100 w"
0B
0J"
0c
0M"
1R"
1T"
0R
0b
0+"
0W"
0}
1:"
1*
0!"
1P"
1A
0Q
0a
0*"
0Q"
1;"
1p
0O
0`
0)"
0C"
0<"
1V"
1|
09"
1+
1d
1""
0@"
1~
0O"
0D
1K"
0=
0N
0W
0'"
18"
0\"
0N"
0G"
1Z"
0k"
13"
14"
15"
16"
17"
0]"
1>"
1A"
0{
1B"
1D"
0H"
0I"
0S
1X"
1^"
0,"
1."
1F
0y
1F"
1L"
1Y"
1`"
1e
b101 $
b101 (
b1101 #
b1101 '
b1100011 "
b1100011 &
#100000
1""
1C
1U"
1x
b1010011 !
b1010011 w"
1B
0!"
0S"
1P"
1E
1R
1+"
0:"
0*
0X"
1^"
0A
1Q
1*"
0;"
0Y"
0~
1R"
0O"
0D
0p
0K"
1O
1)"
0|
19"
1W"
0_"
1+
08
0d
17
0@"
1T
1b
1o
1=
1N
1'"
08"
1\"
1}
0Q"
1G"
1J"
1c
1M"
1a
1n
1k"
04"
05"
06"
07"
0V"
1]"
0<"
1>"
1A"
0C"
0B"
1I"
0S
1`
1j
1,"
0."
03"
0F"
19
0F
0L"
1W
1i
b1 $
b1 (
b10010 #
b10010 '
b1100101 "
b1100101 &
#110000
0T"
1S"
06
0C
1P"
b11110010 !
b11110010 w"
05
0B
0R"
1x
1!"
0)
0o
0+"
07
0s"
14
1A
0n
0*"
1Q"
1p
0N"
1~
0m"
0j
0)"
0>"
1<"
18
1d
0B"
0S
1U"
1_"
0l"
00
0=
0i
0'"
0\"
0L"
0}
0O"
0D
0Z"
0k"
14"
15"
16"
17"
0]"
1V"
19"
1A"
1W"
1:"
0*
1?"
0@"
1X"
0^"
0,"
1."
18"
1U
0\
1|
1;"
1Y"
1F
b101 $
b101 (
b1110110 #
b1110110 '
b1101 "
b1101 &
#120000
b1100001 !
b1100001 w"
0M"
1C
1P"
1T
1B
0!"
0N"
1S"
1E
1K"
1o
1B"
0S
18
16
0A
1n
0p
0~
1L"
0R"
0O"
0D
0J"
0c
15
1j
0|
1d
1""
0A"
07
1?"
0@"
0I"
0+
0_"
1)
1+"
1=
1i
08"
1\"
1}
1Q"
1T"
1Z"
1s"
04
1*"
1k"
05"
06"
07"
0V"
1]"
04"
19"
1<"
0>"
1C"
1W"
0:"
1*
0X"
1^"
1m"
1)"
1,"
0."
0/"
09
1G
0e
0;"
0Y"
1l"
10
1y
1z
1'"
b1 $
b1 (
b10001100 #
b10001100 '
b11101101 "
b11101101 &
#130000
0U"
0K"
0S"
1c
1M"
1!"
b11000100 !
b11000100 w"
0B"
0S
0)
0b
0+"
1R"
0L"
0Q"
1p
1~
0s"
0a
0*"
07
0C"
1A"
0<"
1V"
09"
0m"
0_
0)"
1Z"
0P"
18"
0\"
0}
1_"
0j"
0V
0("
0X"
0^"
1+
13"
14"
15"
16"
17"
0Y"
1T"
1O"
1D
1."
0]"
1i"
0>"
1J"
1W"
0c"
1:"
0*
1@"
1D"
0I"
1-"
1h"
1/"
1H"
1|
0;"
0,
0F
0G
1e
b10 $
b10 (
b11000101 #
b11000101 '
b11000110 "
b11000110 &
#140000
b1100101 !
b1100101 w"
1S
1^"
1K"
0!"
1U"
1+"
06
0J"
0c
0~
1*"
0w
05
0:"
17
1)"
0s
1Q"
1{
1("
0G"
0r
1v"
19"
1<"
1C"
0*
0H"
0I"
0-
19
0z
0;"
1F"
1,
b1110111 #
b1110111 '
b11100101 "
b11100101 &
#150000
0T"
b11110 !
b11110 w"
1S"
1x
1!"
0R"
0R
0o
1+"
07
1)
16
0C
0Q
0n
0M"
1w
1a
1~
1*"
1P"
1s"
15
0?
0P
0[
0j
1B"
0S
1s
1_
1)"
1U"
1m"
0;
0M
0Z
0h
0C"
1L"
1G"
1r
1V
0{
1("
0O"
0D
0J"
0c
0Z"
1j"
0v"
0i"
0A"
1:"
0*
0@"
1D"
0I"
1X"
0^"
1c"
1-
0g
0,"
1n"
03"
0F"
0U
1\
1z
1;"
1Y"
1F
b110 $
b110 (
b11110010 #
b11110010 '
b10001111 "
b10001111 &
#160000
0U"
06
05
0J
0a
0S"
0P"
b101101 !
b101101 w"
0_
1C
0p
1v"
1I
0]
1?
1R"
0c
1O"
1D
1)
0R
1o
11
1H
1;
07
0K"
1N"
1s"
1Q
0b
1n
1\"
1d"
0Q"
1T"
1M"
1Z"
1r"
1P
1[
1j
1+"
0n"
09"
0<"
1A"
0C"
1J"
1:"
1*
1I"
1S
0X"
0^"
0c"
1o"
1M
1Z
1g
1h
1&"
0["
0h"
13"
1H"
09
1;"
1L"
0Y"
0e
b100 $
b100 (
b11000101 #
b11000101 '
b11101000 "
b11101000 &
#170000
1S"
b1000010 !
b1000010 w"
0R"
0)
0o
1R
0s"
0n
1U"
16
1J
1P"
1!"
1C
1b
0m"
0j
15
0~
1p
1B
1a
0l"
0i
01
0:"
1*
0?"
1@"
0I
1O"
1D
0x
0f"
1_
0k"
0\"
0d"
0;"
0v"
0H
1{
0N"
0G"
1c
0e"
0u"
1]
0-"
19"
1>"
0W"
0-
0B"
0H"
0S
07
1X"
1^"
1c"
0>
1["
1G
0z
1F"
0L"
1Q"
0Y"
0`"
19
1U
0\
b101 $
b101 (
b101101 #
b101101 '
b10111101 "
b10111101 &
